typed_units/__init__.py
typed_units/py.typed
typed_units/root_unit.py
types_units/__init__.pyi
types_units/abstract.pyi
types_units/compatibility.pyi
types_units/composed_unit.pyi
types_units/exception.pyi
types_units/leaf_unit.pyi
types_units/named_composed_unit.pyi
types_units/predefined.pyi
types_units/py.typed
types_units/quantity.pyi
types_units/registry.pyi
types_units/si.pyi
python_typed_units-0.0.0.dist-info/METADATA
python_typed_units-0.0.0.dist-info/WHEEL
python_typed_units-0.0.0.dist-info/top_level.txt
python_typed_units-0.0.0.dist-info/RECORD
